starter_api/__init__.py
starter_api/api.py
starter_api/info.py
starter_api/private_api.py
starter_api-0.1.3.dist-info/DESCRIPTION.rst
starter_api-0.1.3.dist-info/METADATA
starter_api-0.1.3.dist-info/RECORD
starter_api-0.1.3.dist-info/WHEEL
starter_api-0.1.3.dist-info/metadata.json
starter_api-0.1.3.dist-info/top_level.txt
