Metadata-Version: 2.0
Name: starter-api
Version: 0.1.3
Summary: Client for Starter Server API
Home-page: https://github.com/rw-meta/starter-py-client
Author: Artur Geraschenko
Author-email: arturgspb@gmail.com
License: MIT
Platform: UNKNOWN
Classifier: Development Status :: 3 - Alpha
Classifier: Programming Language :: Python :: 2
Classifier: Programming Language :: Python :: 2.7
Requires-Dist: requests (==2.10.0)
